README
setup.py
appteka/__init__.py
appteka/cli.py
appteka/config.py
appteka/distrib.py
appteka/io.py
appteka/reporter.py
appteka/routine.py
appteka/simple_signal.py
appteka.egg-info/PKG-INFO
appteka.egg-info/SOURCES.txt
appteka.egg-info/dependency_links.txt
appteka.egg-info/requires.txt
appteka.egg-info/top_level.txt
appteka/pyqt/__init__.py
appteka/pyqt/code_text_edit.py
appteka/pyqt/control_states.py
appteka/pyqt/gui.py
appteka/pyqt/select_item_dialog.py
appteka/sqlite/__init__.py
appteka/sqlite/testing.py
test/test_cli.py
test/test_code_text_edit.py
test/test_config.py
test/test_distrib.py
test/test_gui.py
test/test_io.py
test/test_reporter.py
test/test_select_item_dialog.py
test/test_simple_signal.py